smefit/__init__.py
smefit/analyze/__init__.py
smefit/analyze/assets/index.css
smefit/analyze/assets/index.html
smefit/analyze/assets/style.css
smefit/analyze/chi2_utils.py
smefit/analyze/coefficients_utils.py
smefit/analyze/contours_2d.py
smefit/analyze/correlations.py
smefit/analyze/fisher.py
smefit/analyze/html_utils.py
smefit/analyze/latex_tools.py
smefit/analyze/logo.png
smefit/analyze/pca.py
smefit/analyze/report.py
smefit/analyze/spider.py
smefit/analyze/summary.py
smefit/basis_rotation.py
smefit/chi2.py
smefit/cli/__init__.py
smefit/cli/base.py
smefit/coefficients.py
smefit/compute_theory.py
smefit/covmat.py
smefit/fit_manager.py
smefit/loader.py
smefit/log.py
smefit/optimize/__init__.py
smefit/optimize/analytic.py
smefit/optimize/mc.py
smefit/optimize/ultranest.py
smefit/postfit/__init__.py
smefit/prefit/__init__.py
smefit/projections/__init__.py
smefit/rge/__init__.py
smefit/rge/rge.py
smefit/rge/wcxf.py
smefit/runner.py
smefit/utils.py
smefit-3.1.1.dist-info/LICENSE
smefit-3.1.1.dist-info/METADATA
smefit-3.1.1.dist-info/WHEEL
smefit-3.1.1.dist-info/entry_points.txt
smefit-3.1.1.dist-info/RECORD
