Metadata-Version: 2.3
Name: smefit
Version: 3.1.1
Summary: Standard Model Effective Field Theory Fitter
License: LICENSE
Keywords: packaging,dependency,infer,pyproject.toml
Author: Jaco ter Hoeve
Author-email: jaco.ter.hoeve@ed.ac.uk
Requires-Python: >=3.10,<3.13
Classifier: License :: Other/Proprietary License
Classifier: Operating System :: Unix
Classifier: Programming Language :: Python
Classifier: Programming Language :: Python :: 3
Classifier: Programming Language :: Python :: 3.10
Classifier: Programming Language :: Python :: 3.11
Classifier: Programming Language :: Python :: 3.12
Classifier: Topic :: Scientific/Engineering
Classifier: Topic :: Scientific/Engineering :: Physics
Requires-Dist: arviz (>=0.18.0,<0.19.0)
Requires-Dist: click (>=8.1.3,<9.0.0)
Requires-Dist: cma (>=3.2.2,<4.0.0)
Requires-Dist: jax (>=0.5.1,<0.6.0)
Requires-Dist: jaxlib (>=0.5.1,<0.6.0)
Requires-Dist: matplotlib (>=3.9.0,<4.0.0)
Requires-Dist: numpy (>=1.21.5,<2.0.0)
Requires-Dist: pandas (>=2.2.2,<3.0.0)
Requires-Dist: pyyaml (>=6.0.1,<7.0.0)
Requires-Dist: rich (>=13.7.1,<14.0.0)
Requires-Dist: scipy (>=1.8.0,<2.0.0)
Requires-Dist: seaborn (>=0.13.2,<0.14.0)
Requires-Dist: ultranest (>=4.4.0,<5.0.0)
Requires-Dist: wilson (>=2.4,<3.0)
Project-URL: Homepage, https://lhcfitnikhef.github.io/smefit_release/
Project-URL: Repository, https://github.com/LHCfitNikhef/smefit_release
